containerdiff-0.4.dist-info/DESCRIPTION.rst
containerdiff-0.4.dist-info/WHEEL
containerdiff-0.4.dist-info/METADATA
containerdiff-0.4.dist-info/metadata.json
containerdiff-0.4.dist-info/top_level.txt
containerdiff-0.4.dist-info/RECORD
containerdiff/undocker.py
containerdiff/__init__.py
containerdiff/filter.json
containerdiff/package_managers.py
containerdiff/run.py
containerdiff/filter.py
containerdiff/modules/__init__.py
containerdiff/modules/history.py
containerdiff/modules/metadata.py
containerdiff/modules/packages.py
containerdiff/modules/files.py
containerdiff-0.4.data/scripts/containerdiff
